<?xml version="1.0" encoding="UTF-8"?>
<objects serializationModel="Studio.01.09.00">
    <object class="Event" id="{00da1fb1-b7d2-417d-a2bf-23b68bcea37a}">
        <property name="name">
            <value>1KD</value>
        </property>
        <property name="outputFormat">
            <value>2</value>
        </property>
        <relationship name="folder">
            <destination>{0114fcc0-4d89-4a62-aca4-fa8d001b9ce2}</destination>
        </relationship>
        <relationship name="mixer">
            <destination>{8cd3e9b5-859e-4c37-b78d-83c9997d52f6}</destination>
        </relationship>
        <relationship name="masterTrack">
            <destination>{fa1a0310-8601-490e-9d8e-0459a6890ce4}</destination>
        </relationship>
        <relationship name="mixerInput">
            <destination>{665bba56-19fb-4560-a8a2-ca34fd593f40}</destination>
        </relationship>
        <relationship name="automatableProperties">
            <destination>{c41b7a65-a31a-4428-a9e0-1c0662e9f290}</destination>
        </relationship>
        <relationship name="markerTracks">
            <destination>{15e4030b-ecb4-42dd-be85-2e6a6a96f258}</destination>
        </relationship>
        <relationship name="groupTracks">
            <destination>{d170c929-f3b7-4c88-8951-856a5fbf98c0}</destination>
        </relationship>
        <relationship name="timeline">
            <destination>{4dad292c-4d84-4bcd-a3b7-27b2fab9916c}</destination>
        </relationship>
        <relationship name="banks">
            <destination>{b0c9b29b-eece-4ff5-b063-0ec5ae50166d}</destination>
        </relationship>
    </object>
    <object class="EventMixer" id="{8cd3e9b5-859e-4c37-b78d-83c9997d52f6}">
        <relationship name="masterBus">
            <destination>{7e152374-a6c9-41f3-af64-a2791a91bad9}</destination>
        </relationship>
    </object>
    <object class="MasterTrack" id="{fa1a0310-8601-490e-9d8e-0459a6890ce4}">
        <relationship name="mixerGroup">
            <destination>{7e152374-a6c9-41f3-af64-a2791a91bad9}</destination>
        </relationship>
    </object>
    <object class="MixerInput" id="{665bba56-19fb-4560-a8a2-ca34fd593f40}">
        <relationship name="effectChain">
            <destination>{cd35598b-f3d8-4a61-9886-2faf91f4b060}</destination>
        </relationship>
        <relationship name="panner">
            <destination>{cf5a4b2f-cb03-43f2-a02c-ace458148ed6}</destination>
        </relationship>
        <relationship name="output">
            <destination>{96b63df1-c493-4f23-93eb-f7f1748fbb19}</destination>
        </relationship>
    </object>
    <object class="EventAutomatableProperties" id="{c41b7a65-a31a-4428-a9e0-1c0662e9f290}"/>
    <object class="MarkerTrack" id="{15e4030b-ecb4-42dd-be85-2e6a6a96f258}"/>
    <object class="GroupTrack" id="{d170c929-f3b7-4c88-8951-856a5fbf98c0}">
        <relationship name="modules">
            <destination>{7870612b-c9f3-45e0-911a-27a0336899c1}</destination>
        </relationship>
        <relationship name="mixerGroup">
            <destination>{37c7e0f4-5a42-42b0-a463-b997838f4fdc}</destination>
        </relationship>
    </object>
    <object class="Timeline" id="{4dad292c-4d84-4bcd-a3b7-27b2fab9916c}">
        <relationship name="modules">
            <destination>{7870612b-c9f3-45e0-911a-27a0336899c1}</destination>
        </relationship>
    </object>
    <object class="EventMixerMaster" id="{7e152374-a6c9-41f3-af64-a2791a91bad9}">
        <relationship name="effectChain">
            <destination>{31152f78-778e-4dd1-beb8-e8175a4bb152}</destination>
        </relationship>
        <relationship name="panner">
            <destination>{1ca4b4b0-be98-4170-9166-ddd1591ea23a}</destination>
        </relationship>
        <relationship name="mixer">
            <destination>{8cd3e9b5-859e-4c37-b78d-83c9997d52f6}</destination>
        </relationship>
    </object>
    <object class="MixerBusEffectChain" id="{cd35598b-f3d8-4a61-9886-2faf91f4b060}">
        <relationship name="effects">
            <destination>{c7c6c276-b0e5-401a-b3fe-b2d1f5f96014}</destination>
        </relationship>
    </object>
    <object class="MixerBusPanner" id="{cf5a4b2f-cb03-43f2-a02c-ace458148ed6}"/>
    <object class="SingleSound" id="{7870612b-c9f3-45e0-911a-27a0336899c1}">
        <property name="length">
            <value>11.703208333333333</value>
        </property>
        <relationship name="audioFile">
            <destination>{a5a9a98b-b052-47af-aa8a-79b381defc3b}</destination>
        </relationship>
    </object>
    <object class="EventMixerGroup" id="{37c7e0f4-5a42-42b0-a463-b997838f4fdc}">
        <property name="name">
            <value>Audio 1</value>
        </property>
        <relationship name="effectChain">
            <destination>{65e2df54-c53e-49ad-bbb9-b36cf54fbfa4}</destination>
        </relationship>
        <relationship name="panner">
            <destination>{6cb96250-2621-4d32-9e93-1ee64bb6b90b}</destination>
        </relationship>
        <relationship name="output">
            <destination>{7e152374-a6c9-41f3-af64-a2791a91bad9}</destination>
        </relationship>
    </object>
    <object class="MixerBusEffectChain" id="{31152f78-778e-4dd1-beb8-e8175a4bb152}">
        <relationship name="effects">
            <destination>{75ca28ca-ccc2-4b2c-b544-f153538ddd78}</destination>
            <destination>{4edb6c45-fb8f-465c-8878-2fb107140f2a}</destination>
        </relationship>
    </object>
    <object class="MixerBusPanner" id="{1ca4b4b0-be98-4170-9166-ddd1591ea23a}"/>
    <object class="MixerBusFader" id="{c7c6c276-b0e5-401a-b3fe-b2d1f5f96014}"/>
    <object class="MixerBusEffectChain" id="{65e2df54-c53e-49ad-bbb9-b36cf54fbfa4}">
        <relationship name="effects">
            <destination>{38db3042-bc96-445a-9ebe-643d07ff6ec2}</destination>
        </relationship>
    </object>
    <object class="MixerBusPanner" id="{6cb96250-2621-4d32-9e93-1ee64bb6b90b}"/>
    <object class="MixerBusFader" id="{75ca28ca-ccc2-4b2c-b544-f153538ddd78}"/>
    <object class="SpatialiserEffect" id="{4edb6c45-fb8f-465c-8878-2fb107140f2a}"/>
    <object class="MixerBusFader" id="{38db3042-bc96-445a-9ebe-643d07ff6ec2}"/>
</objects>
